MANIFEST.in
setup.py
gc_monitor/__init__.py
gc_monitor/monitor.py
gc_monitor.egg-info/PKG-INFO
gc_monitor.egg-info/SOURCES.txt
gc_monitor.egg-info/dependency_links.txt
gc_monitor.egg-info/entry_points.txt
gc_monitor.egg-info/not-zip-safe
gc_monitor.egg-info/requires.txt
gc_monitor.egg-info/top_level.txt
gc_monitor/static/bootstrap.min.css
gc_monitor/static/bootstrap.min.js
gc_monitor/static/jquery.min.js
gc_monitor/static/bootstrap-3.3.7-dist/css/bootstrap-theme.css
gc_monitor/static/bootstrap-3.3.7-dist/css/bootstrap-theme.css.map
gc_monitor/static/bootstrap-3.3.7-dist/css/bootstrap-theme.min.css
gc_monitor/static/bootstrap-3.3.7-dist/css/bootstrap-theme.min.css.map
gc_monitor/static/bootstrap-3.3.7-dist/css/bootstrap.css
gc_monitor/static/bootstrap-3.3.7-dist/css/bootstrap.css.map
gc_monitor/static/bootstrap-3.3.7-dist/css/bootstrap.min.css
gc_monitor/static/bootstrap-3.3.7-dist/css/bootstrap.min.css.map
gc_monitor/static/bootstrap-3.3.7-dist/fonts/glyphicons-halflings-regular.eot
gc_monitor/static/bootstrap-3.3.7-dist/fonts/glyphicons-halflings-regular.svg
gc_monitor/static/bootstrap-3.3.7-dist/fonts/glyphicons-halflings-regular.ttf
gc_monitor/static/bootstrap-3.3.7-dist/fonts/glyphicons-halflings-regular.woff
gc_monitor/static/bootstrap-3.3.7-dist/fonts/glyphicons-halflings-regular.woff2
gc_monitor/static/bootstrap-3.3.7-dist/js/bootstrap.js
gc_monitor/static/bootstrap-3.3.7-dist/js/bootstrap.min.js
gc_monitor/static/bootstrap-3.3.7-dist/js/npm.js
gc_monitor/templates/index.html