Metadata-Version: 1.0
Name: gc-monitor
Version: 1.0.3
Summary: Test Flask Sample
Home-page: UNKNOWN
Author: ChenJie
Author-email: chenjie@galachip.com
License: UNKNOWN
Platform: UNKNOWN
